timeter/__init__.py
timeter/py.typed
timeter-1.0.0.dist-info/LICENSE
timeter-1.0.0.dist-info/METADATA
timeter-1.0.0.dist-info/WHEEL
timeter-1.0.0.dist-info/top_level.txt
timeter-1.0.0.dist-info/RECORD
