Metadata-Version: 2.1
Name: timeter
Version: 1.0.0
Summary: A handy set of tools to measure your code execution time
Author: SyberiaK
License: MIT License
Project-URL: Homepage, https://github.com/SyberiaK/timeter
Project-URL: Issues, https://github.com/SyberiaK/timeter/issues
Classifier: Development Status :: 6 - Mature
Classifier: Intended Audience :: Developers
Classifier: License :: OSI Approved :: MIT License
Classifier: Operating System :: OS Independent
Classifier: Programming Language :: Python :: 3.8
Classifier: Programming Language :: Python :: 3.9
Classifier: Programming Language :: Python :: 3.10
Classifier: Programming Language :: Python :: 3.11
Classifier: Programming Language :: Python :: 3.12
Classifier: Programming Language :: Python :: 3.13
Classifier: Topic :: Utilities
Classifier: Typing :: Typed
Requires-Python: >=3.8
License-File: LICENSE
